pybehave/Pybehave.py
pybehave/__init__.py
pybehave/Components/AnalogInput.py
pybehave/Components/AnalogOutput.py
pybehave/Components/BinaryInput.py
pybehave/Components/Both.py
pybehave/Components/Component.py
pybehave/Components/Input.py
pybehave/Components/OEBinaryInput.py
pybehave/Components/Output.py
pybehave/Components/SerialTTL.py
pybehave/Components/Speaker.py
pybehave/Components/StimJim.py
pybehave/Components/Stimmer.py
pybehave/Components/TimedToggle.py
pybehave/Components/Toggle.py
pybehave/Components/TouchBinaryInput.py
pybehave/Components/TouchScreen.py
pybehave/Components/Video.py
pybehave/Components/WaveformStim.py
pybehave/Components/__init__.py
pybehave/Elements/BarPressElement.py
pybehave/Elements/ButtonElement.py
pybehave/Elements/CircleLightElement.py
pybehave/Elements/Element.py
pybehave/Elements/FanElement.py
pybehave/Elements/FoodLightElement.py
pybehave/Elements/IndicatorElement.py
pybehave/Elements/InfoBoxElement.py
pybehave/Elements/LabelElement.py
pybehave/Elements/NosePokeElement.py
pybehave/Elements/RectangleLightElement.py
pybehave/Elements/ShockElement.py
pybehave/Elements/SoundElement.py
pybehave/Elements/TouchScreenElement.py
pybehave/Elements/__init__.py
pybehave/Elements/draw_filled_arc.py
pybehave/Elements/draw_light.py
pybehave/Events/CSVEventLogger.py
pybehave/Events/EventLogger.py
pybehave/Events/EventWidget.py
pybehave/Events/FileEventLogger.py
pybehave/Events/LoggerEvent.py
pybehave/Events/ManualWidget.py
pybehave/Events/OENetworkLogger.py
pybehave/Events/OEWidget.py
pybehave/Events/PybEvents.py
pybehave/Events/SubjectConfigWidget.py
pybehave/Events/TerminalWidget.py
pybehave/Events/Widget.py
pybehave/Events/__init__.py
pybehave/GUIs/Colors.py
pybehave/GUIs/GUI.py
pybehave/GUIs/SequenceGUI.py
pybehave/GUIs/__init__.py
pybehave/Sources/BayesOptSource.py
pybehave/Sources/HikVisionSource.py
pybehave/Sources/NIDAQSource.py
pybehave/Sources/OESource.py
pybehave/Sources/OSControllerSource.py
pybehave/Sources/SerialSource.py
pybehave-1.0.19.dist-info/LICENSE
pybehave-1.0.19.dist-info/METADATA
pybehave-1.0.19.dist-info/WHEEL
pybehave-1.0.19.dist-info/entry_points.txt
pybehave-1.0.19.dist-info/top_level.txt
pybehave-1.0.19.dist-info/RECORD
